result/__init__.py
result/errors.py
result/py.typed
result/result.py
typing_result-0.1.2.dist-info/LICENSE
typing_result-0.1.2.dist-info/METADATA
typing_result-0.1.2.dist-info/WHEEL
typing_result-0.1.2.dist-info/RECORD
