Metadata-Version: 2.1
Name: typing-result
Version: 0.1.2
Summary: A python implementation of the Result type, based on the rust language
License: MIT
Author: William Osteimer Cardoso dos Anjos
Author-email: wosteimer1@gmail.com
Requires-Python: >=3.10,<4.0
Classifier: Development Status :: 5 - Production/Stable
Classifier: License :: OSI Approved :: MIT License
Classifier: Programming Language :: Python :: 3
Classifier: Programming Language :: Python :: 3.10
Classifier: Programming Language :: Python :: 3.11
Classifier: Programming Language :: Python :: 3.10
Project-URL: github, https://github.com/wosteimer/py-result
